{"stats":{"minecraft:dropped":{"minecraft:moss_carpet":4,"minecraft:wheat_seeds":1,"minecraft:raw_copper":11,"minecraft:diamond":18,"philipsruins:cracked_bone":4,"minecraft:diamond_shovel":1,"pointblank:gunmetal_nugget":12,"minecraft:diamond_sword":5,"minecraft:dirt":7,"projectvibrantjourneys:light_brown_bark_mushroom":1,"minecraft:oak_wood":5,"minecraft:leather_boots":1,"minecraft:oak_sapling":6,"minecraft:iron_leggings":3,"minecraft:bone_meal":1,"minecraft:iron_axe":1},"minecraft:killed":{"alexsmobs:raccoon":1,"minecraft:zombie":14,"ecologics:squirrel":1,"minecraft:stray":12},"minecraft:mined":{"minecraft:deepslate_tiles":4,"create:deepslate_zinc_ore":10,"minecraft:deepslate_diamond_ore":3,"psg:potassium_ore":4,"psg:deepslate_sulphur_ore":44,"minecraft:crafting_table":1,"philipsruins:bone_chunk_block":1,"philipsruins:bone_bricks":1,"projectvibrantjourneys:twigs":2,"minecraft:oak_wood":2,"philipsruins:cracked_bone":2,"minecraft:white_stained_glass_pane":1,"minecraft:copper_ore":2,"minecraft:lapis_ore":4,"mcore:deepslate_titanium_ore":1,"minecraft:wall_torch":2,"minecraft:spawner":7,"minecraft:deepslate_copper_ore":1,"minecraft:skeleton_skull":1,"minecraft:hay_block":21,"philipsruins:chiseled_bone_bricks":1,"immersive_weathering:mossy_stone":1,"philipsruins:bone_bricks_wall":1,"minecraft:cobbled_deepslate":2,"minecraft:andesite":15,"minecraft:gold_block":3,"minecraft:grass":1,"minecraft:polished_deepslate":4,"minecraft:cracked_deepslate_tiles":1,"minecraft:oak_log":53,"projectvibrantjourneys:short_grass":6,"minecraft:deepslate_iron_ore":3,"minecraft:vine":2,"minecraft:gravel":3,"minecraft:dirt":7,"pointblank:workstation":2,"minecraft:stone":40,"projectvibrantjourneys:oak_hollow_log":4,"minecraft:deepslate":38},"minecraft:crafted":{"minecraft:oak_planks":12,"minecraft:crafting_table":1,"minecraft:bread":9,"minecraft:diamond_helmet":1,"minecraft:stick":2,"minecraft:iron_pickaxe":1,"minecraft:diamond_boots":1,"minecraft:torch":8,"minecraft:wheat":27},"minecraft:used":{"minecraft:diamond_boots":1,"minecraft:torch":6,"minecraft:crafting_table":2,"minecraft:iron_axe":4,"minecraft:bread":18,"minecraft:iron_pickaxe":200,"philipsruins:cracked_bone":1,"minecraft:diamond_sword":107,"pointblank:workstation":1,"minecraft:cobblestone":12,"minecraft:iron_leggings":1},"minecraft:picked_up":{"minecraft:cracked_deepslate_tiles":1,"minecraft:crafting_table":1,"minecraft:andesite":15,"minecraft:gold_block":3,"minecraft:flint":1,"create:raw_zinc":10,"minecraft:oak_log":24,"minecraft:gunpowder":2,"projectvibrantjourneys:oak_hollow_log":4,"minecraft:string":1,"minecraft:polished_deepslate":3,"minecraft:lapis_lazuli":29,"minecraft:dirt":14,"minecraft:moss_carpet":4,"mcore:raw_titanium":1,"minecraft:raw_copper":11,"minecraft:iron_leggings":2,"philipsruins:chiseled_bone_bricks":1,"minecraft:bone":6,"minecraft:apple":2,"minecraft:wheat_seeds":1,"minecraft:deepslate_tiles":3,"minecraft:cobbled_deepslate":36,"minecraft:iron_ingot":3,"minecraft:iron_nugget":7,"pointblank:workstation":2,"projectvibrantjourneys:light_brown_bark_mushroom":1,"minecraft:stick":22,"minecraft:raw_iron":3,"philipsruins:cracked_bone":2,"psg:raw_potassium":7,"minecraft:torch":4,"pointblank:gunmetal_nugget":12,"minecraft:gravel":1,"psg:sulphur":112,"minecraft:oak_wood":5,"minecraft:arrow":11,"minecraft:diamond":4,"minecraft:hay_block":21,"projectvibrantjourneys:orange_bark_mushroom":1,"minecraft:oak_sapling":6,"projectvibrantjourneys:twigs":2,"minecraft:skeleton_skull":1,"minecraft:cobblestone":40},"minecraft:custom":{"lootr:looted_stat":23,"minecraft:mob_kills":28,"minecraft:interact_with_crafting_table":6,"minecraft:damage_dealt_resisted":0,"minecraft:time_since_death":35199,"minecraft:climb_one_cm":4838,"minecraft:time_since_rest":35199,"minecraft:damage_absorbed":0,"minecraft:sprint_one_cm":182656,"minecraft:damage_taken":639,"minecraft:walk_one_cm":96719,"minecraft:drop":24,"minecraft:damage_dealt":4386,"minecraft:swim_one_cm":432,"minecraft:talked_to_villager":12,"minecraft:fly_one_cm":177354,"minecraft:open_chest":3,"minecraft:crouch_one_cm":998,"minecraft:play_time":35199,"minecraft:sneak_time":349,"minecraft:walk_under_water_one_cm":58,"minecraft:interact_with_brewingstand":3,"minecraft:jump":744,"minecraft:interact_with_blast_furnace":1,"minecraft:walk_on_water_one_cm":761,"minecraft:total_world_time":35199,"minecraft:fall_one_cm":21267}},"DataVersion":3465}